<?xml version="1.0" encoding="utf-8" ?>
<dwsync>
<file name="blank.gif" server="ftp.ierisl.com" local="129926977774617178" remote="129955689600000000" />
<file name="colorpicker_background.png" server="ftp.ierisl.com" local="129926977774647178" remote="129955689600000000" />
<file name="colorpicker_hex.png" server="ftp.ierisl.com" local="129926977774677178" remote="129955689600000000" />
<file name="colorpicker_hsb_b.png" server="ftp.ierisl.com" local="129926977774697178" remote="129955689600000000" />
<file name="colorpicker_hsb_h.png" server="ftp.ierisl.com" local="129926977774717178" remote="129955689600000000" />
<file name="colorpicker_hsb_s.png" server="ftp.ierisl.com" local="129926977774747178" remote="129955689600000000" />
<file name="colorpicker_indic.gif" server="ftp.ierisl.com" local="129926977774767178" remote="129955689600000000" />
<file name="colorpicker_overlay.png" server="ftp.ierisl.com" local="129926977774797178" remote="129955689600000000" />
<file name="colorpicker_rgb_b.png" server="ftp.ierisl.com" local="129926977774817178" remote="129955689600000000" />
<file name="colorpicker_rgb_g.png" server="ftp.ierisl.com" local="129926977774847178" remote="129955689600000000" />
<file name="colorpicker_rgb_r.png" server="ftp.ierisl.com" local="129926977774867178" remote="129955689600000000" />
<file name="colorpicker_select.gif" server="ftp.ierisl.com" local="129926977774887178" remote="129955689600000000" />
<file name="colorpicker_submit.png" server="ftp.ierisl.com" local="129926977774917178" remote="129955689600000000" />
<file name="select.png" server="ftp.ierisl.com" local="129926977774937178" remote="129955689600000000" />
</dwsync>